[
    {"category": "fifa", "liked": true},
    {"category": "elden ring", "liked": true},
    {"category": "nba 2k", "liked": true},
    {"category": "call of duty", "liked": true},
    {"category": "rocket league", "liked": true},
    {"category": "overwatch", "liked": true},
    {"category": "minecraft", "liked": true},
    {"category": "virtual reality", "liked": false},
    {"category": "augmented reality", "liked": false},
    {"category": "game modding", "liked": false},
    {"category": "e-sports management", "liked": false},
    {"category": "sports analytics", "liked": false},
    {"category": "game development", "liked": false},
    {"category": "interactive media", "liked": false},
    {"category": "3D modeling", "liked": false},
    {"category": "digital art tools", "liked": false},
    {"category": "photography styles", "liked": false},
    {"category": "adventure tourism", "liked": false},
    {"category": "educational technology", "liked": false},
    {"category": "student mental health", "liked": false},
    {"category": "entrepreneurship mindset", "liked": false},
    {"category": "biomechanics", "liked": false},
    {"category": "nutrition science", "liked": false},
    {"category": "pet care", "liked": false},
    {"category": "animal welfare", "liked": false},
    {"category": "space architecture", "liked": false},
    {"category": "smart farming", "liked": false},
    {"category": "data protection", "liked": false}
]
